vmpck_distributions/Binomialdistribution.py
vmpck_distributions/Gaussiandistribution.py
vmpck_distributions/Generaldistribution.py
vmpck_distributions/__init__.py
vmpck_distributions-0.1.dist-info/METADATA
vmpck_distributions-0.1.dist-info/WHEEL
vmpck_distributions-0.1.dist-info/top_level.txt
vmpck_distributions-0.1.dist-info/RECORD
